examples/example.py
examples/snapshot.py
pycola3.libs/libgomp-a34b3233.so.1.0.0
docs/conf.py
pycola3-0.0.7.dist-info/top_level.txt
pycola3-0.0.7.dist-info/WHEEL
pycola3-0.0.7.dist-info/LICENSE
pycola3-0.0.7.dist-info/METADATA
pycola3-0.0.7.dist-info/COPYING
pycola3-0.0.7.dist-info/RECORD
pycola3/growth.py
pycola3/__init__.py
pycola3/box_smooth.cpython-38-x86_64-linux-gnu.so
pycola3/aux.py
pycola3/evolve.py
pycola3/ic.py
pycola3/potential.cpython-38-x86_64-linux-gnu.so
pycola3/acceleration.cpython-38-x86_64-linux-gnu.so
pycola3/cic.cpython-38-x86_64-linux-gnu.so
